speech_bot_helpers/__init__.py
speech_bot_helpers/clients.py
speech_bot_helpers/exceptions.py
speech_bot_helpers/wrappers.py
speech_bot_helpers-0.2.4.dist-info/METADATA
speech_bot_helpers-0.2.4.dist-info/WHEEL
speech_bot_helpers-0.2.4.dist-info/RECORD
