Metadata-Version: 2.1
Name: speech-bot-helpers
Version: 0.2.4
Summary: 
Author: Eugene Shcherba
Requires-Python: >=3.11,<4.0
Classifier: Programming Language :: Python :: 3
Classifier: Programming Language :: Python :: 3.11
Requires-Dist: aiobotocore (>=2.5.0,<3.0.0)
Requires-Dist: wrapt (>=1.15.0,<2.0.0)
